icesat2_toolkit/__init__.py
icesat2_toolkit/convert.py
icesat2_toolkit/convert_delta_time.py
icesat2_toolkit/fit.py
icesat2_toolkit/spatial.py
icesat2_toolkit/time.py
icesat2_toolkit/tools.py
icesat2_toolkit/utilities.py
icesat2_toolkit/version.py
icesat2_toolkit/data/leap-seconds.list
icesat2_toolkit/io/ATL03.py
icesat2_toolkit/io/ATL06.py
icesat2_toolkit/io/ATL07.py
icesat2_toolkit/io/ATL10.py
icesat2_toolkit/io/ATL11.py
icesat2_toolkit/io/ATL12.py
icesat2_toolkit/io/__init__.py
icesat2_toolkit-1.3.1.data/scripts/MPI_DEM_ICESat2_ATL03.py
icesat2_toolkit-1.3.1.data/scripts/MPI_DEM_ICESat2_ATL06.py
icesat2_toolkit-1.3.1.data/scripts/MPI_DEM_ICESat2_ATL11.py
icesat2_toolkit-1.3.1.data/scripts/MPI_ICESat2_ATL03.py
icesat2_toolkit-1.3.1.data/scripts/MPI_ICESat2_ATL03_histogram.py
icesat2_toolkit-1.3.1.data/scripts/MPI_reduce_ICESat2_ATL03_RGI.py
icesat2_toolkit-1.3.1.data/scripts/MPI_reduce_ICESat2_ATL06_RGI.py
icesat2_toolkit-1.3.1.data/scripts/MPI_reduce_ICESat2_ATL06_drainages.py
icesat2_toolkit-1.3.1.data/scripts/MPI_reduce_ICESat2_ATL06_grounded.py
icesat2_toolkit-1.3.1.data/scripts/MPI_reduce_ICESat2_ATL06_ice_shelves.py
icesat2_toolkit-1.3.1.data/scripts/MPI_reduce_ICESat2_ATL11_RGI.py
icesat2_toolkit-1.3.1.data/scripts/MPI_reduce_ICESat2_ATL11_drainages.py
icesat2_toolkit-1.3.1.data/scripts/MPI_reduce_ICESat2_ATL11_grounded.py
icesat2_toolkit-1.3.1.data/scripts/MPI_reduce_ICESat2_ATL11_ice_shelves.py
icesat2_toolkit-1.3.1.data/scripts/convert_ICESat2_format.py
icesat2_toolkit-1.3.1.data/scripts/copy_scf_ICESat2_files.py
icesat2_toolkit-1.3.1.data/scripts/nsidc_icesat2_associated.py
icesat2_toolkit-1.3.1.data/scripts/nsidc_icesat2_convert.py
icesat2_toolkit-1.3.1.data/scripts/nsidc_icesat2_dragann.py
icesat2_toolkit-1.3.1.data/scripts/nsidc_icesat2_sync.py
icesat2_toolkit-1.3.1.data/scripts/nsidc_icesat2_sync_s3.py
icesat2_toolkit-1.3.1.data/scripts/reduce_ICESat2_ATL06_raster.py
icesat2_toolkit-1.3.1.data/scripts/reduce_ICESat2_ATL07_raster.py
icesat2_toolkit-1.3.1.dist-info/LICENSE
icesat2_toolkit-1.3.1.dist-info/METADATA
icesat2_toolkit-1.3.1.dist-info/WHEEL
icesat2_toolkit-1.3.1.dist-info/top_level.txt
icesat2_toolkit-1.3.1.dist-info/RECORD
