Metadata-Version: 2.1
Name: icesat2-toolkit
Version: 1.3.1
Summary: Python tools for obtaining and working with elevation data from the NASA ICESat-2 mission
Home-page: https://github.com/tsutterley/read-ICESat-2
Author: Tyler Sutterley
Author-email: tsutterl@uw.edu
License: MIT
Keywords: ICESat-2 laser altimetry,ATLAS,surface elevation and change
Classifier: Development Status :: 3 - Alpha
Classifier: Intended Audience :: Science/Research
Classifier: Topic :: Scientific/Engineering :: Physics
Classifier: License :: OSI Approved :: MIT License
Classifier: Programming Language :: Python :: 3
Classifier: Programming Language :: Python :: 3.5
Classifier: Programming Language :: Python :: 3.6
Classifier: Programming Language :: Python :: 3.7
Classifier: Programming Language :: Python :: 3.8
License-File: LICENSE
Requires-Dist: future
Requires-Dist: lxml
Requires-Dist: numpy
Requires-Dist: paramiko
Requires-Dist: pyproj
Requires-Dist: python-dateutil
Requires-Dist: scipy
Requires-Dist: scp
Requires-Dist: timescale
